mac_alias/__init__.py
mac_alias/alias.py
mac_alias/bookmark.py
mac_alias/osx.py
mac_alias/utils.py
mac_alias-2.2.2.dist-info/LICENSE
mac_alias-2.2.2.dist-info/METADATA
mac_alias-2.2.2.dist-info/WHEEL
mac_alias-2.2.2.dist-info/entry_points.txt
mac_alias-2.2.2.dist-info/top_level.txt
mac_alias-2.2.2.dist-info/RECORD
