Metadata-Version: 2.1
Name: mac_alias
Version: 2.2.2
Summary: Generate/parse Mac OS Alias records from Python
Home-page: http://alastairs-place.net/projects/mac_alias
Author: Alastair Houghton
Author-email: alastair@alastairs-place.net
Maintainer: Russell Keith-Magee
Maintainer-email: russell@keith-magee.com
License: MIT License
Project-URL: Source, https://github.com/al45stair/mac_alias
Keywords: mac_alias
Platform: darwin
Classifier: Development Status :: 5 - Production/Stable
Classifier: License :: OSI Approved :: MIT License
Classifier: Programming Language :: Python :: 3
Classifier: Programming Language :: Python :: 3.7
Classifier: Programming Language :: Python :: 3.8
Classifier: Programming Language :: Python :: 3.9
Classifier: Programming Language :: Python :: 3.10
Classifier: Programming Language :: Python :: 3.11
Classifier: Programming Language :: Python :: 3.12
Classifier: Programming Language :: Python :: 3 :: Only
Classifier: Topic :: Desktop Environment
Classifier: Topic :: Software Development :: Libraries :: Python Modules
Requires-Python: >=3.7
Provides-Extra: dev
Provides-Extra: test
Provides-Extra: docs
License-File: LICENSE
